processscheduler/__init__.py
processscheduler/__main__.py
processscheduler/base.py
processscheduler/buffer.py
processscheduler/constraint.py
processscheduler/excel_io.py
processscheduler/first_order_logic.py
processscheduler/function.py
processscheduler/indicator.py
processscheduler/indicator_constraint.py
processscheduler/objective.py
processscheduler/plotter.py
processscheduler/problem.py
processscheduler/resource.py
processscheduler/resource_constraint.py
processscheduler/solution.py
processscheduler/solver.py
processscheduler/task.py
processscheduler/task_constraint.py
processscheduler/util.py
processscheduler-2.0.0.dist-info/LICENSE.txt
processscheduler-2.0.0.dist-info/METADATA
processscheduler-2.0.0.dist-info/WHEEL
processscheduler-2.0.0.dist-info/RECORD
