Metadata-Version: 2.1
Name: ProcessScheduler
Version: 2.0.0
Summary: A Python package for automatic and optimized resource scheduling
Home-page: https://processscheduler.github.io/
License: GPL-3.0-or-later
Author: Thomas Paviot
Author-email: tpaviot@gmail.com
Requires-Python: >=3.8,<4.0
Classifier: Development Status :: 4 - Beta
Classifier: Intended Audience :: Developers
Classifier: Intended Audience :: Financial and Insurance Industry
Classifier: Intended Audience :: Healthcare Industry
Classifier: Intended Audience :: Manufacturing
Classifier: License :: OSI Approved :: GNU General Public License v3 or later (GPLv3+)
Classifier: Natural Language :: English
Classifier: Operating System :: OS Independent
Classifier: Programming Language :: Python :: 3
Classifier: Programming Language :: Python :: 3.8
Classifier: Programming Language :: Python :: 3.9
Classifier: Programming Language :: Python :: 3.10
Classifier: Programming Language :: Python :: 3.11
Classifier: Programming Language :: Python :: 3.12
Classifier: Topic :: Office/Business :: Scheduling
Classifier: Topic :: Software Development :: Libraries
Classifier: Typing :: Typed
Requires-Dist: pydantic (>=2.5)
Requires-Dist: z3-solver (==4.12.5.0)
